{"frames": {

"AdvancePlanning.png":
{
	"frame": {"x":1448,"y":259,"w":256,"h":198},
	"rotated": false,
	"trimmed": false,
	"spriteSourceSize": {"x":0,"y":0,"w":256,"h":198},
	"sourceSize": {"w":256,"h":198}
},
"Angelica.png":
{
	"frame": {"x":1707,"y":259,"w":256,"h":198},
	"rotated": false,
	"trimmed": false,
	"spriteSourceSize": {"x":0,"y":0,"w":256,"h":198},
	"sourceSize": {"w":256,"h":198}
},
"Bastard.png":
{
	"frame": {"x":0,"y":518,"w":256,"h":198},
	"rotated": false,
	"trimmed": false,
	"spriteSourceSize": {"x":0,"y":0,"w":256,"h":198},
	"sourceSize": {"w":256,"h":198}
},
"Bentley.png":
{
	"frame": {"x":259,"y":518,"w":256,"h":198},
	"rotated": false,
	"trimmed": false,
	"spriteSourceSize": {"x":0,"y":0,"w":256,"h":198},
	"sourceSize": {"w":256,"h":198}
},
"BitchCharacter.png":
{
	"frame": {"x":0,"y":0,"w":178,"h":256},
	"rotated": false,
	"trimmed": false,
	"spriteSourceSize": {"x":0,"y":0,"w":178,"h":256},
	"sourceSize": {"w":178,"h":256}
},
"BitchCharacterBack.png":
{
	"frame": {"x":181,"y":0,"w":178,"h":256},
	"rotated": false,
	"trimmed": false,
	"spriteSourceSize": {"x":0,"y":0,"w":178,"h":256},
	"sourceSize": {"w":178,"h":256}
},
"ClothGolem.png":
{
	"frame": {"x":518,"y":518,"w":256,"h":198},
	"rotated": false,
	"trimmed": false,
	"spriteSourceSize": {"x":0,"y":0,"w":256,"h":198},
	"sourceSize": {"w":256,"h":198}
},
"CoordinatedBlitz.png":
{
	"frame": {"x":777,"y":518,"w":256,"h":198},
	"rotated": false,
	"trimmed": false,
	"spriteSourceSize": {"x":0,"y":0,"w":256,"h":198},
	"sourceSize": {"w":256,"h":198}
},
"DescentOfTheSwarm.png":
{
	"frame": {"x":1036,"y":518,"w":256,"h":198},
	"rotated": false,
	"trimmed": false,
	"spriteSourceSize": {"x":0,"y":0,"w":256,"h":198},
	"sourceSize": {"w":256,"h":198}
},
"FoilCharacter.png":
{
	"frame": {"x":362,"y":0,"w":178,"h":256},
	"rotated": false,
	"trimmed": false,
	"spriteSourceSize": {"x":0,"y":0,"w":178,"h":256},
	"sourceSize": {"w":178,"h":256}
},
"FoilCharacterBack.png":
{
	"frame": {"x":543,"y":0,"w":178,"h":256},
	"rotated": false,
	"trimmed": false,
	"spriteSourceSize": {"x":0,"y":0,"w":178,"h":256},
	"sourceSize": {"w":178,"h":256}
},
"ForgottenAssailant.png":
{
	"frame": {"x":1295,"y":518,"w":256,"h":198},
	"rotated": false,
	"trimmed": false,
	"spriteSourceSize": {"x":0,"y":0,"w":256,"h":198},
	"sourceSize": {"w":256,"h":198}
},
"GrueCharacter.png":
{
	"frame": {"x":724,"y":0,"w":178,"h":256},
	"rotated": false,
	"trimmed": false,
	"spriteSourceSize": {"x":0,"y":0,"w":178,"h":256},
	"sourceSize": {"w":178,"h":256}
},
"GrueCharacterBack.png":
{
	"frame": {"x":905,"y":0,"w":178,"h":256},
	"rotated": false,
	"trimmed": false,
	"spriteSourceSize": {"x":0,"y":0,"w":178,"h":256},
	"sourceSize": {"w":178,"h":256}
},
"HailOfBlades.png":
{
	"frame": {"x":1554,"y":518,"w":256,"h":198},
	"rotated": false,
	"trimmed": false,
	"spriteSourceSize": {"x":0,"y":0,"w":256,"h":198},
	"sourceSize": {"w":256,"h":198}
},
"ImpCharacter.png":
{
	"frame": {"x":1086,"y":0,"w":178,"h":256},
	"rotated": false,
	"trimmed": false,
	"spriteSourceSize": {"x":0,"y":0,"w":178,"h":256},
	"sourceSize": {"w":178,"h":256}
},
"ImpCharacterBack.png":
{
	"frame": {"x":1267,"y":0,"w":178,"h":256},
	"rotated": false,
	"trimmed": false,
	"spriteSourceSize": {"x":0,"y":0,"w":178,"h":256},
	"sourceSize": {"w":178,"h":256}
},
"ImperiousControl.png":
{
	"frame": {"x":0,"y":719,"w":256,"h":198},
	"rotated": false,
	"trimmed": false,
	"spriteSourceSize": {"x":0,"y":0,"w":256,"h":198},
	"sourceSize": {"w":256,"h":198}
},
"ParianCharacter.png":
{
	"frame": {"x":1448,"y":0,"w":178,"h":256},
	"rotated": false,
	"trimmed": false,
	"spriteSourceSize": {"x":0,"y":0,"w":178,"h":256},
	"sourceSize": {"w":178,"h":256}
},
"ParianCharacterBack.png":
{
	"frame": {"x":1629,"y":0,"w":178,"h":256},
	"rotated": false,
	"trimmed": false,
	"spriteSourceSize": {"x":0,"y":0,"w":178,"h":256},
	"sourceSize": {"w":178,"h":256}
},
"RegentCharacter.png":
{
	"frame": {"x":1810,"y":0,"w":178,"h":256},
	"rotated": false,
	"trimmed": false,
	"spriteSourceSize": {"x":0,"y":0,"w":178,"h":256},
	"sourceSize": {"w":178,"h":256}
},
"RegentCharacterBack.png":
{
	"frame": {"x":0,"y":259,"w":178,"h":256},
	"rotated": false,
	"trimmed": false,
	"spriteSourceSize": {"x":0,"y":0,"w":178,"h":256},
	"sourceSize": {"w":178,"h":256}
},
"SkitterCharacter.png":
{
	"frame": {"x":181,"y":259,"w":178,"h":256},
	"rotated": false,
	"trimmed": false,
	"spriteSourceSize": {"x":0,"y":0,"w":178,"h":256},
	"sourceSize": {"w":178,"h":256}
},
"SkitterCharacterBack.png":
{
	"frame": {"x":362,"y":259,"w":178,"h":256},
	"rotated": false,
	"trimmed": false,
	"spriteSourceSize": {"x":0,"y":0,"w":178,"h":256},
	"sourceSize": {"w":178,"h":256}
},
"StingingSwarm.png":
{
	"frame": {"x":259,"y":719,"w":256,"h":198},
	"rotated": false,
	"trimmed": false,
	"spriteSourceSize": {"x":0,"y":0,"w":256,"h":198},
	"sourceSize": {"w":256,"h":198}
},
"TattletaleCharacter.png":
{
	"frame": {"x":543,"y":259,"w":178,"h":256},
	"rotated": false,
	"trimmed": false,
	"spriteSourceSize": {"x":0,"y":0,"w":178,"h":256},
	"sourceSize": {"w":178,"h":256}
},
"TattletaleCharacterBack.png":
{
	"frame": {"x":724,"y":259,"w":178,"h":256},
	"rotated": false,
	"trimmed": false,
	"spriteSourceSize": {"x":0,"y":0,"w":178,"h":256},
	"sourceSize": {"w":178,"h":256}
},
"TenebrousCloud.png":
{
	"frame": {"x":518,"y":719,"w":256,"h":198},
	"rotated": false,
	"trimmed": false,
	"spriteSourceSize": {"x":0,"y":0,"w":256,"h":198},
	"sourceSize": {"w":256,"h":198}
},
"TheUndersidersDeckBack.png":
{
	"frame": {"x":905,"y":259,"w":178,"h":256},
	"rotated": false,
	"trimmed": false,
	"spriteSourceSize": {"x":0,"y":0,"w":178,"h":256},
	"sourceSize": {"w":178,"h":256}
},
"TheUndersidersInstructions.png":
{
	"frame": {"x":1086,"y":259,"w":178,"h":256},
	"rotated": false,
	"trimmed": false,
	"spriteSourceSize": {"x":0,"y":0,"w":178,"h":256},
	"sourceSize": {"w":178,"h":256}
},
"TheUndersidersInstructionsBack.png":
{
	"frame": {"x":1267,"y":259,"w":178,"h":256},
	"rotated": false,
	"trimmed": false,
	"spriteSourceSize": {"x":0,"y":0,"w":178,"h":256},
	"sourceSize": {"w":178,"h":256}
},
"WarlordsOfBrockton.png":
{
	"frame": {"x":777,"y":719,"w":256,"h":198},
	"rotated": false,
	"trimmed": false,
	"spriteSourceSize": {"x":0,"y":0,"w":256,"h":198},
	"sourceSize": {"w":256,"h":198}
},
"WatchfulSwarm.png":
{
	"frame": {"x":1036,"y":719,"w":256,"h":198},
	"rotated": false,
	"trimmed": false,
	"spriteSourceSize": {"x":0,"y":0,"w":256,"h":198},
	"sourceSize": {"w":256,"h":198}
}},
"meta": {
	"app": "https://www.codeandweb.com/texturepacker",
	"version": "1.0",
	"image": "TheUndersidersAtlas0.png",
	"format": "RGBA8888",
	"size": {"w":2048,"h":2048},
	"scale": "1",
	"smartupdate": "$TexturePacker:SmartUpdate:6288d76d0a31b732e5ac64d31368e0d7:be565e0b4a5873f2599a80bd68046026:701e5a03e78cb1edd909d0f76b53e470$"
}
}
